pnadc/__init__.py
pnadc/constants.py
pnadc/downloads.py
pnadc/pipeline.py
pnadc/processing.py
pnadc/settings.py
pnadc/utils.py
py_pnadc-0.1.5.dist-info/licenses/LICENSE.md
py_pnadc-0.1.5.dist-info/METADATA
py_pnadc-0.1.5.dist-info/WHEEL
py_pnadc-0.1.5.dist-info/top_level.txt
py_pnadc-0.1.5.dist-info/RECORD
