Metadata-Version: 2.4
Name: py-pnadc
Version: 0.1.5
Summary: Unofficial package for PNADC microdata (IBGE)
Home-page: https://github.com/andre-kmp/py-pnadc
Author: André Klaic
Author-email: andreklaic@gmail.com
Classifier: Programming Language :: Python :: 3
Classifier: License :: OSI Approved :: MIT License
Classifier: Operating System :: OS Independent
Requires-Python: >=3.8
License-File: LICENSE.md
Requires-Dist: pandas
Requires-Dist: fastparquet
Requires-Dist: requests
Requires-Dist: bs4
Requires-Dist: chardet
Dynamic: author
Dynamic: author-email
Dynamic: classifier
Dynamic: description
Dynamic: description-content-type
Dynamic: home-page
Dynamic: license-file
Dynamic: requires-dist
Dynamic: requires-python
Dynamic: summary
